[
  {
    "title": "经验值和头衔",
    "remark": "调整格式、",
    "date": "2023/11/10",
    "contributor": "景明1102"
  },
  {
    "title": "深海栖舰列表",
    "remark": "修正笔误",
    "date": "2023/11/9",
    "contributor": "Oda-shitsukiri"
  },
  {
    "title": "季节性/2023年秋刀鱼祭典",
    "remark": "内容扩充",
    "date": "2023/11/3",
    "contributor": "OwenNiu"
  },
  {
    "title": "任务/最新任务",
    "remark": "修饰语句 修正笔误",
    "date": "2023/11/3",
    "contributor": "OwenNiu"
  },
  {
    "title": "清霜",
    "remark": "内容扩充",
    "date": "2023/10/11",
    "contributor": "Krayton sendai"
  }
]